ML-Algo/DataCleaning.py
ML-Algo/FetchData.py
ML-Algo/Predictions.py
ML-Algo/Series_Data.py
ML-Algo/Series_Time.py
ML-Algo/__init__.py
ML_Algo/DataCleaning.py
ML_Algo/FetchData.py
ML_Algo/Predictions.py
ML_Algo/Series_Data.py
ML_Algo/Series_Time.py
ML_Algo/TestRun.py
ML_Algo/__init__.py
ML_Algo-1.3.2.dist-info/METADATA
ML_Algo-1.3.2.dist-info/WHEEL
ML_Algo-1.3.2.dist-info/top_level.txt
ML_Algo-1.3.2.dist-info/RECORD
